{
  "collectionName": "components_pdp_pdp_countries_lists",
  "info": {
    "displayName": "Pdp-CountriesList",
    "description": ""
  },
  "options": {},
  "attributes": {
    "title": {
      "type": "string"
    },
    "desc": {
      "type": "text"
    },
    "disclaimer": {
      "type": "text"
    },
    "country": {
      "displayName": "country",
      "type": "component",
      "repeatable": true,
      "component": "pdp.country"
    },
    "type": {
      "type": "enumeration",
      "enum": [
        "pdp-countries-list"
      ],
      "default": "pdp-countries-list",
      "required": true
    }
  }
}
