{
  "collectionName": "components_pdp_pdp_bike_insurance_premium_rates",
  "info": {
    "displayName": "Pdp - bikeInsurancePremiumRate",
    "description": ""
  },
  "options": {},
  "attributes": {
    "title": {
      "type": "string"
    },
    "desc": {
      "type": "richtext"
    },
    "tableData": {
      "type": "component",
      "repeatable": true,
      "component": "pdp.compare-policy-section"
    },
    "type": {
      "type": "enumeration",
      "enum": [
        "pdp-bike-insurance-premium"
      ],
      "default": "pdp-bike-insurance-premium",
      "required": true
    }
  }
}
