{
	"collectionName": "components_contact_us_office_cards",
	"info": {
		"displayName": "officeCards",
		"description": ""
	},
	"options": {},
	"attributes": {
		"card1": {
			"displayName": "card1",
			"type": "component",
			"repeatable": false,
			"component": "contact-us.card1",
			"required": true
		},
		"card2": {
			"displayName": "card2",
			"type": "component",
			"repeatable": false,
			"component": "contact-us.card2",
			"required": true
		},
		"card3": {
			"displayName": "card3",
			"type": "component",
			"repeatable": false,
			"component": "contact-us.card3",
			"required": true
		}
	}
}
