{
  "collectionName": "components_dashboard_track_claim_cards",
  "info": {
    "displayName": "trackClaimCard"
  },
  "options": {},
  "attributes": {
    "title": {
      "required": true,
      "type": "string"
    },
    "subtitle": {
      "required": true,
      "type": "string"
    },
    "desktopImage": {
      "required": true,
      "type": "string"
    },
    "notificationImage": {
      "required": true,
      "type": "string"
    },
    "mobileHealthImage": {
      "required": true,
      "type": "string"
    },
    "mobileMotorImage": {
      "required": true,
      "type": "string"
    },
    "buttonText": {
      "required": true,
      "type": "string"
    },
    "buttonTextClevertapEvent": {
      "displayName": "ClevertapButtonEvent",
      "type": "component",
      "repeatable": false,
      "component": "shared.clevertap-button-event"
    }
  }
}
